x7/__init__.py
x7/geom/__init__.py
x7/geom/__version__.py
x7/geom/anim.py
x7/geom/anim_simple.py
x7/geom/bezier.py
x7/geom/colors.py
x7/geom/drawing.py
x7/geom/geom.py
x7/geom/imagehelp.py
x7/geom/iters.py
x7/geom/model.py
x7/geom/needs_test.py
x7/geom/platform.py
x7/geom/plot_utils.py
x7/geom/plot_viewer.py
x7/geom/shell_tools.py
x7/geom/testing.py
x7/geom/transform.py
x7/geom/typing.py
x7/geom/utils.py
x7/geom/vec_field.py
x7_geom-0.7.3.dist-info/LICENSE
x7_geom-0.7.3.dist-info/METADATA
x7_geom-0.7.3.dist-info/WHEEL
x7_geom-0.7.3.dist-info/entry_points.txt
x7_geom-0.7.3.dist-info/top_level.txt
x7_geom-0.7.3.dist-info/RECORD
